{
  "latest_version": "v2.6.3",
  "repo_name": "3a-console-esp32-template-sm",
  "last_commit_date": "2025-08-20 13:20:05",
  "last_updated": "2025-08-20 11:52:40",
  "version_changes": [
    {
      "version": "v2.6.3",
      "date": "2025-08-19",
      "components": [
        "virtual"
      ],
      "description": "Implement sensor-specific error tracking and virtual device attribution"
    },
    {
      "version": "v2.6.2",
      "date": "2025-08-18",
      "components": [
        "digital"
      ],
      "description": "Added timestamps to audio-switcher log / digital sensor logs"
    },
    {
      "version": "v2.6.1",
      "date": "2025-08-12",
      "components": [
        "digital"
      ],
      "description": "Added hold time to digital switch"
    },
    {
      "version": "v2.6.0",
      "date": "2025-08-07",
      "components": [
        "core"
      ],
      "description": "Implement SSL memory failure recovery with automatic restartSL memory failure recovery with automatic restart"
    },
    {
      "version": "v2.5.0",
      "date": "2025-08-07",
      "components": [
        "MODBUS"
      ],
      "description": "Data priorization for MODBUS sensors"
    },
    {
      "version": "v2.4.0",
      "date": "2025-08-07",
      "components": [
        "core"
      ],
      "description": "Memory logging and mock data for easier testing and debugging"
    },
    {
      "version": "v2.3.2",
      "date": "2025-07-09",
      "components": [
        "MODBUS"
      ],
      "description": "Fixed MODBUS directional control implementation"
    },
    {
      "version": "v2.3.1",
      "date": "2025-06-19",
      "components": [
        "digital"
      ],
      "description": "Enhanced digital switch with configurable labels and immediate logging"
    },
    {
      "version": "v2.3.0",
      "date": "2025-06-17",
      "components": [
        "core"
      ],
      "description": "More robust wifi initialization implemented"
    },
    {
      "version": "v2.2.2",
      "date": "2025-06-17",
      "components": [
        "digital"
      ],
      "description": "Added support for digital switches ()digital switches, relays etc.)"
    },
    {
      "version": "v2.2.1",
      "date": "2025-05-20",
      "components": [
        "OneWire"
      ],
      "description": "OneWire bus scan upon sensor initialization for easier debugging"
    },
    {
      "version": "v2.2.0",
      "date": "2025-05-20",
      "components": [
        "core"
      ],
      "description": "Deep setting comparison to trigger sensor reinitialization on all sensor setting updates"
    },
    {
      "version": "v2.1.7",
      "date": "2025-05-20",
      "components": [
        "algae"
      ],
      "description": "Added algae sensor"
    },
    {
      "version": "v2.1.6",
      "date": "2025-05-14",
      "components": [
        "digital"
      ],
      "description": "Digital sensor now saves total count in non volatile memory"
    },
    {
      "version": "v2.1.5",
      "date": "2025-05-14",
      "components": [
        "OneWire"
      ],
      "description": "Onewire mapping send as event and minor log layout change"
    },
    {
      "version": "v2.1.4",
      "date": "2025-05-20",
      "components": [
        "OneWire"
      ],
      "description": "Fixed sensor index for address based onewire sensor initialization"
    },
    {
      "version": "v2.1.3",
      "date": "2025-05-20",
      "components": [
        "core"
      ],
      "description": "Optimized version tracking for easier management"
    },
    {
      "version": "v2.1.2",
      "date": "2025-05-13",
      "components": [
        "core"
      ],
      "description": "Improved handling of device naming for single device configurations"
    },
    {
      "version": "v2.1.1",
      "date": "2025-05-13",
      "components": [
        "MODBUS"
      ],
      "description": "MODBUS now supports TTL to RS485 with direction pin"
    },
    {
      "version": "v2.1.0",
      "date": "2025-05-13",
      "components": [
        "core"
      ],
      "description": "Updated wifi credential initialization"
    },
    {
      "version": "v2.0.0",
      "date": "2025-05-12",
      "components": [
        "virtual"
      ],
      "description": "Virtual devices uses master/slave configuration and hardware config is implemented to prevent wrong pin configuration"
    },
    {
      "version": "v1.3.2",
      "date": "2025-04-23",
      "components": [
        "virtual"
      ],
      "description": "Fixed virtual device settings fetching"
    },
    {
      "version": "v1.3.1",
      "date": "2025-03-28",
      "components": [
        "digital"
      ],
      "description": "Patched problem with edge, state detection of digital sensors"
    },
    {
      "version": "v1.3.0",
      "date": "2025-03-27",
      "components": [
        "virtual"
      ],
      "description": "Added support for virtual devices"
    },
    {
      "version": "v1.2.2",
      "date": "2025-03-19",
      "components": [
        "core"
      ],
      "description": "Updated event send logic, to lessen trafic"
    },
    {
      "version": "v1.2.1",
      "date": "2025-03-19",
      "components": [
        "core"
      ],
      "description": "Version 1.2.1 - Stable version"
    },
    {
      "version": "v1.1.2",
      "date": "2025-03-15",
      "components": [
        "core"
      ],
      "description": "Fix inconsistent handling of log intervals"
    },
    {
      "version": "v1.1.1",
      "date": "2025-03-15",
      "components": [
        "MODBUS"
      ],
      "description": "Improved MODBUS sensor implementation"
    },
    {
      "version": "v1.1.0",
      "date": "2025-03-14",
      "components": [
        "core"
      ],
      "description": "Implement device configuration management system"
    },
    {
      "version": "v1.0.0",
      "date": "2025-03-14",
      "components": [
        "core"
      ],
      "description": "Initial consolidated template"
    }
  ],
  "timeline_events": [
    {
      "device": "water-system-temperatures",
      "device_name": "Water System Temperatures",
      "date": "2025-05-16",
      "version": "v2.2.1",
      "location": "Technician room - Box left of door",
      "event_type": "previous_deployment",
      "description": "Previous deployment"
    },
    {
      "device": "water-system-temperatures",
      "device_name": "Water System Temperatures",
      "date": "2025-05-16",
      "version": "v2.2.1",
      "location": "Technician room - Box left of door",
      "event_type": "update_deployment",
      "description": "Device updated (production)"
    },
    {
      "device": "water-heater-power-consumption",
      "device_name": "Water Heater Power Consumption",
      "date": "2025-05-16",
      "version": "v2.2.0",
      "location": "Technician room - Inside electrical box next to power meter for heaters",
      "event_type": "previous_deployment",
      "description": "Previous deployment"
    },
    {
      "device": "water-heater-power-consumption",
      "device_name": "Water Heater Power Consumption",
      "date": "2025-05-16",
      "version": "v2.2.0",
      "location": "Technician room - Inside electrical box next to power meter for heaters",
      "event_type": "update_deployment",
      "description": "Device updated (production)"
    },
    {
      "device": "sauna-temperature-and-humidity",
      "device_name": "Sauna Temperature and Humidity",
      "date": "2025-05-16",
      "version": "v2.2.0",
      "location": "Basement (left side) - On top of box next to fridge",
      "event_type": "previous_deployment",
      "description": "Previous deployment"
    },
    {
      "device": "sauna-temperature-and-humidity",
      "device_name": "Sauna Temperature and Humidity",
      "date": "2025-05-16",
      "version": "v2.2.0",
      "location": "Basement (left side) - On top of box next to fridge",
      "event_type": "update_deployment",
      "description": "Device updated (production)"
    },
    {
      "device": "sauna-power-consumption",
      "device_name": "Sauna Power Consumption",
      "date": "2025-05-16",
      "version": "v2.6.0",
      "location": "Basement (left side) - Rear electrical box",
      "event_type": "previous_deployment",
      "description": "Previous deployment"
    },
    {
      "device": "sauna-power-consumption",
      "device_name": "Sauna Power Consumption",
      "date": "2025-05-16",
      "version": "v2.6.0",
      "location": "Basement (left side) - Rear electrical box",
      "event_type": "update_deployment",
      "description": "Device updated (production)"
    },
    {
      "device": "algae-monitor",
      "device_name": "Algae Sensor",
      "date": "2025-05-15",
      "version": "v2.1.7",
      "location": "Under floor next to pool filter",
      "event_type": "deployment",
      "description": "Device deployed"
    },
    {
      "device": "mog-tank-water-sensor",
      "device_name": "MOG Tank Water Sensor",
      "date": "2025-05-14",
      "version": "v2.2.0",
      "location": "Basement - right side (by MOG tank)",
      "event_type": "previous_deployment",
      "description": "Previous deployment"
    },
    {
      "device": "mog-tank-water-sensor",
      "device_name": "MOG Tank Water Sensor",
      "date": "2025-05-14",
      "version": "v2.2.0",
      "location": "Basement - right side (by MOG tank)",
      "event_type": "update_deployment",
      "description": "Device updated (production)"
    }
  ],
  "devices": [
    {
      "name": "algae-monitor",
      "version": "v2.1.7",
      "components": [
        "algae",
        "core"
      ],
      "status": "Needs update",
      "location": "Under floor next to pool filter",
      "last_deployed": "2025-05-15",
      "updateReason": "Major or minor version change"
    },
    {
      "name": "audio-switcher",
      "version": "",
      "components": [
        "core",
        "digital_switch"
      ],
      "status": "Never deployed",
      "location": "",
      "last_deployed": "",
      "updateReason": "Device not yet deployed"
    },
    {
      "name": "emergency-door",
      "version": "",
      "components": [
        "core",
        "digital"
      ],
      "status": "Never deployed",
      "location": "",
      "last_deployed": "",
      "updateReason": "Device not yet deployed"
    },
    {
      "name": "mog-tank-water-sensor",
      "version": "v2.2.0",
      "components": [
        "core",
        "digital"
      ],
      "status": "Needs update",
      "location": "Basement - right side (by MOG tank)",
      "last_deployed": "2025-05-14",
      "updateReason": "Major or minor version change"
    },
    {
      "name": "sauna-power-consumption",
      "version": "v2.6.0",
      "components": [
        "core",
        "modbus"
      ],
      "status": "Patch available",
      "location": "Basement (left side) - Rear electrical box",
      "last_deployed": "2025-05-16",
      "updateReason": "Patch update available"
    },
    {
      "name": "sauna-temperature-and-humidity",
      "version": "v2.2.0",
      "components": [
        "core",
        "modbus"
      ],
      "status": "Needs update",
      "location": "Basement (left side) - On top of box next to fridge",
      "last_deployed": "2025-05-16",
      "updateReason": "Major or minor version change"
    },
    {
      "name": "water-heater-power-consumption",
      "version": "v2.2.0",
      "components": [
        "core",
        "modbus"
      ],
      "status": "Needs update",
      "location": "Technician room - Inside electrical box next to power meter for heaters",
      "last_deployed": "2025-05-16",
      "updateReason": "Major or minor version change"
    },
    {
      "name": "water-system-temperatures",
      "version": "v2.2.1",
      "components": [
        "core",
        "onewire",
        "virtual"
      ],
      "status": "Needs update",
      "location": "Technician room - Box left of door",
      "last_deployed": "2025-05-16",
      "updateReason": "Major or minor version change"
    }
  ]
}
